{"K":1,
"K_train":1,
"Kc":20,
"T":"fft",
"Ts":"none",
"anntype":"coordinate",
"batch_size":1000,
"dataset":"ETH-UCY",
"depth":16,
"deterministic":0,
"epochs":800,
"feature_dim":128,
"interval":0.4,
"key_points":"4_8_11",
"log_dir":"./logs/20231011-112651torch_test_2_evsczara1",
"loss":"keyl2",
"lr":0.0004,
"max_agents":50,
"model":"evsc",
"model_name":"torch_test_2_",
"model_type":"agent-based",
"obs_frames":8,
"only_process_trajectory":0,
"partitions":8,
"pmove":-1,
"pred_frames":12,
"preprocess":"100",
"rel_speed":0,
"save_base_dir":"./logs",
"split":"zara1",
"start_test_percent":0.0,
"step":1.0,
"test_step":1,
"use_direction":1,
"use_distance":1,
"use_move_direction":0,
"use_seg_maps":0,
"use_velocity":1}