{"#---------- AgentArgs ----------":0,
"K":1,
"K_train":1,
"Kc":20,
"T":"fft",
"anntype":"coordinate",
"batch_size":1000,
"dataset":"NBA",
"depth":16,
"deterministic":0,
"epochs":900,
"feature_dim":128,
"interval":0.4,
"key_points":"0_5_9",
"log_dir":"./logs/20231023-1657530_5_9_lr_3e-4_vanba50k",
"loss":"keyl2",
"lr":0.0003,
"max_agents":50,
"model":"va",
"model_name":"0_5_9_lr_3e-4_",
"model_type":"agent-based",
"obs_frames":5,
"only_process_trajectory":0,
"pmove":-1,
"pred_frames":10,
"preprocess":"100",
"save_base_dir":"./logs",
"split":"nba50k",
"start_test_percent":0.0,
"step":1.0,
"test_step":1}